[
  {
    "type": "Warrior",
    "Armor": 10,
    "BattleCry": "For pain and for glory! Bytecroft will not sucumb against bugs!",
    "CostStat": 10,
    "KillCount": 0,
    "Abilities": [
      {
        "type": "Defense",
        "Name": "Phalanx Formation",
        "Cost": 5,
        "Rarity": 2,
        "Power": 60,
        "TargetType": 4,
        "ClassType": 0
      },
      {
        "type": "Support",
        "Effect": 1,
        "Name": "Motivational Speech",
        "Cost": 5,
        "Rarity": 2,
        "Power": 80,
        "TargetType": 4,
        "ClassType": 0
      },
      {
        "type": "Defense",
        "Name": "Phalanx Formation",
        "Cost": 5,
        "Rarity": 2,
        "Power": 60,
        "TargetType": 4,
        "ClassType": 0
      },
      {
        "type": "Support",
        "Effect": 2,
        "Name": "Kamikaze",
        "Cost": 0,
        "Rarity": 2,
        "Power": 80,
        "TargetType": 2,
        "ClassType": 0
      }
    ],
    "Name": "Nigga",
    "Level": 23,
    "Hp": 150,
    "MaxHp": 403,
    "Skill": 60,
    "DefenseBuff": 38,
    "IsDefeated": false
  }
]